[
  {
    "cell": "N1_t00",
    "N": 1,
    "t": 0.0,
    "n_total": 400,
    "n_conditioned": 71,
    "n_recovery": 3,
    "n_regression": 10,
    "n_both": 35,
    "n_neither": 23,
    "table_path": "/Users/kabirmoghe/Developer/Thesis/docs/swing_analysis/per_cell/N1_t00__swing_table.csv",
    "png_path": "/Users/kabirmoghe/Developer/Thesis/docs/swing_analysis/per_cell/N1_t00__histograms.png",
    "rows": [
      {
        "category": "both",
        "n": 35,
        "mean_n_train": 3.5142857142857142,
        "mean_n_test": 1.0857142857142856,
        "mean_phase1_buggy": 0.6481417624521073,
        "mean_phase1_fixed": 0.6346924603174603,
        "mean_overlap_buggy": 0.29376488359185193,
        "mean_overlap_fixed": 0.7885487051554633,
        "mean_n_refined_buggy": 1.7142857142857142,
        "mean_n_refined_fixed": 1.7714285714285714
      },
      {
        "category": "regression",
        "n": 10,
        "mean_n_train": 3.5,
        "mean_n_test": 1.1,
        "mean_phase1_buggy": 0.394047619047619,
        "mean_phase1_fixed": 0.42777777777777776,
        "mean_overlap_buggy": 0.3622366405133953,
        "mean_overlap_fixed": 0.817934607031331,
        "mean_n_refined_buggy": 1.6,
        "mean_n_refined_fixed": 0.7
      },
      {
        "category": "recovery",
        "n": 3,
        "mean_n_train": 4.0,
        "mean_n_test": 1.0,
        "mean_phase1_buggy": 0.6000000000000001,
        "mean_phase1_fixed": 0.6844444444444444,
        "mean_overlap_buggy": 0.22569414498763607,
        "mean_overlap_fixed": 0.8864405244858737,
        "mean_n_refined_buggy": 1.3333333333333333,
        "mean_n_refined_fixed": 2.3333333333333335
      },
      {
        "category": "neither",
        "n": 23,
        "mean_n_train": 3.0434782608695654,
        "mean_n_test": 1.0,
        "mean_phase1_buggy": 0.4634027777777778,
        "mean_phase1_fixed": 0.44901960784313727,
        "mean_overlap_buggy": 0.3145778692522067,
        "mean_overlap_fixed": 0.7959344308440114,
        "mean_n_refined_buggy": 1.434782608695652,
        "mean_n_refined_fixed": 1.2173913043478262
      }
    ]
  },
  {
    "cell": "N1_t05",
    "N": 1,
    "t": 0.5,
    "n_total": 400,
    "n_conditioned": 73,
    "n_recovery": 2,
    "n_regression": 8,
    "n_both": 42,
    "n_neither": 21,
    "table_path": "/Users/kabirmoghe/Developer/Thesis/docs/swing_analysis/per_cell/N1_t05__swing_table.csv",
    "png_path": "/Users/kabirmoghe/Developer/Thesis/docs/swing_analysis/per_cell/N1_t05__histograms.png",
    "rows": [
      {
        "category": "both",
        "n": 42,
        "mean_n_train": 3.6904761904761907,
        "mean_n_test": 1.0714285714285714,
        "mean_phase1_buggy": 0.7027539682539683,
        "mean_phase1_fixed": 0.6841954022988506,
        "mean_overlap_buggy": 0.32777407353103677,
        "mean_overlap_fixed": 0.840833999298006,
        "mean_n_refined_buggy": 1.8095238095238095,
        "mean_n_refined_fixed": 1.5952380952380953
      },
      {
        "category": "regression",
        "n": 8,
        "mean_n_train": 3.25,
        "mean_n_test": 1.0,
        "mean_phase1_buggy": 0.6607142857142857,
        "mean_phase1_fixed": 0.6986111111111111,
        "mean_overlap_buggy": 0.2959623424055254,
        "mean_overlap_fixed": 0.7502573860532564,
        "mean_n_refined_buggy": 1.5,
        "mean_n_refined_fixed": 1.5
      },
      {
        "category": "recovery",
        "n": 2,
        "mean_n_train": 4.0,
        "mean_n_test": 1.5,
        "mean_phase1_buggy": 0.13333333333333333,
        "mean_phase1_fixed": 0.6,
        "mean_overlap_buggy": 0.234375,
        "mean_overlap_fixed": 0.9375,
        "mean_n_refined_buggy": 0.5,
        "mean_n_refined_fixed": 1.0
      },
      {
        "category": "neither",
        "n": 21,
        "mean_n_train": 3.0952380952380953,
        "mean_n_test": 1.0476190476190477,
        "mean_phase1_buggy": 0.4725,
        "mean_phase1_fixed": 0.4038888888888889,
        "mean_overlap_buggy": 0.3702054601673654,
        "mean_overlap_fixed": 0.807353793548402,
        "mean_n_refined_buggy": 1.5714285714285714,
        "mean_n_refined_fixed": 1.1428571428571428
      }
    ]
  },
  {
    "cell": "N1_t10",
    "N": 1,
    "t": 1.0,
    "n_total": 400,
    "n_conditioned": 50,
    "n_recovery": 5,
    "n_regression": 5,
    "n_both": 19,
    "n_neither": 21,
    "table_path": "/Users/kabirmoghe/Developer/Thesis/docs/swing_analysis/per_cell/N1_t10__swing_table.csv",
    "png_path": "/Users/kabirmoghe/Developer/Thesis/docs/swing_analysis/per_cell/N1_t10__histograms.png",
    "rows": [
      {
        "category": "both",
        "n": 19,
        "mean_n_train": 3.3157894736842106,
        "mean_n_test": 1.0,
        "mean_phase1_buggy": 0.6596825396825398,
        "mean_phase1_fixed": 0.7620555555555556,
        "mean_overlap_buggy": 0.33065122412959175,
        "mean_overlap_fixed": 0.8367161271613411,
        "mean_n_refined_buggy": 2.0,
        "mean_n_refined_fixed": 1.5789473684210527
      },
      {
        "category": "regression",
        "n": 5,
        "mean_n_train": 3.8,
        "mean_n_test": 1.2,
        "mean_phase1_buggy": 0.585,
        "mean_phase1_fixed": 0.25,
        "mean_overlap_buggy": 0.24787175347040497,
        "mean_overlap_fixed": 0.7894736842105263,
        "mean_n_refined_buggy": 1.4,
        "mean_n_refined_fixed": 0.2
      },
      {
        "category": "recovery",
        "n": 5,
        "mean_n_train": 3.4,
        "mean_n_test": 1.0,
        "mean_phase1_buggy": 0.6875,
        "mean_phase1_fixed": 0.45999999999999996,
        "mean_overlap_buggy": 0.2689746708536461,
        "mean_overlap_fixed": 0.86581947985106,
        "mean_n_refined_buggy": 0.8,
        "mean_n_refined_fixed": 2.0
      },
      {
        "category": "neither",
        "n": 21,
        "mean_n_train": 3.0,
        "mean_n_test": 1.0476190476190477,
        "mean_phase1_buggy": 0.5517156862745098,
        "mean_phase1_fixed": 0.5097222222222222,
        "mean_overlap_buggy": 0.31334820932026164,
        "mean_overlap_fixed": 0.8559633441364698,
        "mean_n_refined_buggy": 1.8095238095238095,
        "mean_n_refined_fixed": 1.5238095238095237
      }
    ]
  },
  {
    "cell": "N2_t00",
    "N": 2,
    "t": 0.0,
    "n_total": 400,
    "n_conditioned": 77,
    "n_recovery": 8,
    "n_regression": 4,
    "n_both": 40,
    "n_neither": 25,
    "table_path": "/Users/kabirmoghe/Developer/Thesis/docs/swing_analysis/per_cell/N2_t00__swing_table.csv",
    "png_path": "/Users/kabirmoghe/Developer/Thesis/docs/swing_analysis/per_cell/N2_t00__histograms.png",
    "rows": [
      {
        "category": "both",
        "n": 40,
        "mean_n_train": 3.425,
        "mean_n_test": 1.025,
        "mean_phase1_buggy": 0.7084635416666667,
        "mean_phase1_fixed": 0.6808333333333334,
        "mean_overlap_buggy": 0.3352352622633335,
        "mean_overlap_fixed": 0.8480372447460383,
        "mean_n_refined_buggy": 1.525,
        "mean_n_refined_fixed": 1.475
      },
      {
        "category": "regression",
        "n": 4,
        "mean_n_train": 3.5,
        "mean_n_test": 1.0,
        "mean_phase1_buggy": 0.47500000000000003,
        "mean_phase1_fixed": 0.4666666666666666,
        "mean_overlap_buggy": 0.51814362734952,
        "mean_overlap_fixed": 0.8328529625092468,
        "mean_n_refined_buggy": 1.75,
        "mean_n_refined_fixed": 1.0
      },
      {
        "category": "recovery",
        "n": 8,
        "mean_n_train": 3.625,
        "mean_n_test": 1.125,
        "mean_phase1_buggy": 0.6277777777777778,
        "mean_phase1_fixed": 0.4732142857142857,
        "mean_overlap_buggy": 0.2701080878485658,
        "mean_overlap_fixed": 0.7290094166880497,
        "mean_n_refined_buggy": 1.125,
        "mean_n_refined_fixed": 1.375
      },
      {
        "category": "neither",
        "n": 25,
        "mean_n_train": 3.24,
        "mean_n_test": 1.04,
        "mean_phase1_buggy": 0.5195238095238095,
        "mean_phase1_fixed": 0.42111111111111116,
        "mean_overlap_buggy": 0.33533835205622997,
        "mean_overlap_fixed": 0.7722977416729366,
        "mean_n_refined_buggy": 1.36,
        "mean_n_refined_fixed": 1.04
      }
    ]
  },
  {
    "cell": "N2_t05",
    "N": 2,
    "t": 0.5,
    "n_total": 400,
    "n_conditioned": 70,
    "n_recovery": 5,
    "n_regression": 3,
    "n_both": 34,
    "n_neither": 28,
    "table_path": "/Users/kabirmoghe/Developer/Thesis/docs/swing_analysis/per_cell/N2_t05__swing_table.csv",
    "png_path": "/Users/kabirmoghe/Developer/Thesis/docs/swing_analysis/per_cell/N2_t05__histograms.png",
    "rows": [
      {
        "category": "both",
        "n": 34,
        "mean_n_train": 3.588235294117647,
        "mean_n_test": 1.0588235294117647,
        "mean_phase1_buggy": 0.7112654320987654,
        "mean_phase1_fixed": 0.6403508771929824,
        "mean_overlap_buggy": 0.3509362170698943,
        "mean_overlap_fixed": 0.8694668302204981,
        "mean_n_refined_buggy": 1.3235294117647058,
        "mean_n_refined_fixed": 1.0
      },
      {
        "category": "regression",
        "n": 3,
        "mean_n_train": 3.0,
        "mean_n_test": 1.0,
        "mean_phase1_buggy": 0.6666666666666666,
        "mean_phase1_fixed": 0.4666666666666667,
        "mean_overlap_buggy": 0.1728395061728395,
        "mean_overlap_fixed": 0.7985543224299065,
        "mean_n_refined_buggy": 0.3333333333333333,
        "mean_n_refined_fixed": 0.6666666666666666
      },
      {
        "category": "recovery",
        "n": 5,
        "mean_n_train": 4.0,
        "mean_n_test": 1.0,
        "mean_phase1_buggy": 0.35,
        "mean_phase1_fixed": 0.4777777777777778,
        "mean_overlap_buggy": 0.2752961144670279,
        "mean_overlap_fixed": 0.7975559985664349,
        "mean_n_refined_buggy": 2.2,
        "mean_n_refined_fixed": 2.0
      },
      {
        "category": "neither",
        "n": 28,
        "mean_n_train": 3.107142857142857,
        "mean_n_test": 1.0357142857142858,
        "mean_phase1_buggy": 0.43746031746031744,
        "mean_phase1_fixed": 0.5003968253968253,
        "mean_overlap_buggy": 0.3537727025200716,
        "mean_overlap_fixed": 0.8038137184525586,
        "mean_n_refined_buggy": 1.5357142857142858,
        "mean_n_refined_fixed": 1.4642857142857142
      }
    ]
  },
  {
    "cell": "N2_t10",
    "N": 2,
    "t": 1.0,
    "n_total": 400,
    "n_conditioned": 79,
    "n_recovery": 10,
    "n_regression": 6,
    "n_both": 43,
    "n_neither": 20,
    "table_path": "/Users/kabirmoghe/Developer/Thesis/docs/swing_analysis/per_cell/N2_t10__swing_table.csv",
    "png_path": "/Users/kabirmoghe/Developer/Thesis/docs/swing_analysis/per_cell/N2_t10__histograms.png",
    "rows": [
      {
        "category": "both",
        "n": 43,
        "mean_n_train": 3.511627906976744,
        "mean_n_test": 1.0465116279069768,
        "mean_phase1_buggy": 0.6068097643097642,
        "mean_phase1_fixed": 0.6671969696969696,
        "mean_overlap_buggy": 0.3210500926553214,
        "mean_overlap_fixed": 0.7815514917469212,
        "mean_n_refined_buggy": 1.6046511627906976,
        "mean_n_refined_fixed": 1.558139534883721
      },
      {
        "category": "regression",
        "n": 6,
        "mean_n_train": 3.6666666666666665,
        "mean_n_test": 1.1666666666666667,
        "mean_phase1_buggy": 0.5319047619047619,
        "mean_phase1_fixed": 0.6785714285714285,
        "mean_overlap_buggy": 0.42518224417565476,
        "mean_overlap_fixed": 0.7678123204644279,
        "mean_n_refined_buggy": 1.8333333333333333,
        "mean_n_refined_fixed": 1.8333333333333333
      },
      {
        "category": "recovery",
        "n": 10,
        "mean_n_train": 3.2,
        "mean_n_test": 1.0,
        "mean_phase1_buggy": 0.4309523809523809,
        "mean_phase1_fixed": 0.38240740740740736,
        "mean_overlap_buggy": 0.3161311040230023,
        "mean_overlap_fixed": 0.810252712211486,
        "mean_n_refined_buggy": 2.0,
        "mean_n_refined_fixed": 1.8
      },
      {
        "category": "neither",
        "n": 20,
        "mean_n_train": 3.45,
        "mean_n_test": 1.15,
        "mean_phase1_buggy": 0.43529411764705883,
        "mean_phase1_fixed": 0.5752777777777777,
        "mean_overlap_buggy": 0.3234285916734288,
        "mean_overlap_fixed": 0.8631078511895138,
        "mean_n_refined_buggy": 1.45,
        "mean_n_refined_fixed": 1.1
      }
    ]
  },
  {
    "cell": "N5_t00",
    "N": 5,
    "t": 0.0,
    "n_total": 400,
    "n_conditioned": 83,
    "n_recovery": 4,
    "n_regression": 8,
    "n_both": 36,
    "n_neither": 35,
    "table_path": "/Users/kabirmoghe/Developer/Thesis/docs/swing_analysis/per_cell/N5_t00__swing_table.csv",
    "png_path": "/Users/kabirmoghe/Developer/Thesis/docs/swing_analysis/per_cell/N5_t00__histograms.png",
    "rows": [
      {
        "category": "both",
        "n": 36,
        "mean_n_train": 3.4444444444444446,
        "mean_n_test": 1.0555555555555556,
        "mean_phase1_buggy": 0.6556481481481483,
        "mean_phase1_fixed": 0.6285555555555554,
        "mean_overlap_buggy": 0.3582752902531105,
        "mean_overlap_fixed": 0.8145463808805508,
        "mean_n_refined_buggy": 1.6388888888888888,
        "mean_n_refined_fixed": 1.5555555555555556
      },
      {
        "category": "regression",
        "n": 8,
        "mean_n_train": 3.75,
        "mean_n_test": 1.0,
        "mean_phase1_buggy": 0.5261904761904762,
        "mean_phase1_fixed": 0.3375,
        "mean_overlap_buggy": 0.3073779666785391,
        "mean_overlap_fixed": 0.8559606929216745,
        "mean_n_refined_buggy": 1.75,
        "mean_n_refined_fixed": 1.125
      },
      {
        "category": "recovery",
        "n": 4,
        "mean_n_train": 2.75,
        "mean_n_test": 1.0,
        "mean_phase1_buggy": 0.7666666666666666,
        "mean_phase1_fixed": 0.49999999999999994,
        "mean_overlap_buggy": 0.4376875776271048,
        "mean_overlap_fixed": 0.8280698853615519,
        "mean_n_refined_buggy": 0.75,
        "mean_n_refined_fixed": 1.25
      },
      {
        "category": "neither",
        "n": 35,
        "mean_n_train": 3.085714285714286,
        "mean_n_test": 1.0285714285714285,
        "mean_phase1_buggy": 0.5522222222222223,
        "mean_phase1_fixed": 0.4662393162393163,
        "mean_overlap_buggy": 0.314414869410961,
        "mean_overlap_fixed": 0.7555262449080662,
        "mean_n_refined_buggy": 1.4857142857142858,
        "mean_n_refined_fixed": 1.2
      }
    ]
  },
  {
    "cell": "N5_t05",
    "N": 5,
    "t": 0.5,
    "n_total": 400,
    "n_conditioned": 77,
    "n_recovery": 8,
    "n_regression": 6,
    "n_both": 44,
    "n_neither": 19,
    "table_path": "/Users/kabirmoghe/Developer/Thesis/docs/swing_analysis/per_cell/N5_t05__swing_table.csv",
    "png_path": "/Users/kabirmoghe/Developer/Thesis/docs/swing_analysis/per_cell/N5_t05__histograms.png",
    "rows": [
      {
        "category": "both",
        "n": 44,
        "mean_n_train": 3.6363636363636362,
        "mean_n_test": 1.0909090909090908,
        "mean_phase1_buggy": 0.6570752895752896,
        "mean_phase1_fixed": 0.6517424242424242,
        "mean_overlap_buggy": 0.3329087935598285,
        "mean_overlap_fixed": 0.764139961625828,
        "mean_n_refined_buggy": 1.8863636363636365,
        "mean_n_refined_fixed": 1.7045454545454546
      },
      {
        "category": "regression",
        "n": 6,
        "mean_n_train": 3.1666666666666665,
        "mean_n_test": 1.0,
        "mean_phase1_buggy": 0.41527777777777775,
        "mean_phase1_fixed": 0.45,
        "mean_overlap_buggy": 0.3049069900529518,
        "mean_overlap_fixed": 0.9283172951034303,
        "mean_n_refined_buggy": 1.5,
        "mean_n_refined_fixed": 0.5
      },
      {
        "category": "recovery",
        "n": 8,
        "mean_n_train": 3.25,
        "mean_n_test": 1.0,
        "mean_phase1_buggy": 0.2033333333333333,
        "mean_phase1_fixed": 0.4883333333333333,
        "mean_overlap_buggy": 0.2929111254111254,
        "mean_overlap_fixed": 0.7024524129683727,
        "mean_n_refined_buggy": 0.75,
        "mean_n_refined_fixed": 1.25
      },
      {
        "category": "neither",
        "n": 19,
        "mean_n_train": 3.473684210526316,
        "mean_n_test": 1.0,
        "mean_phase1_buggy": 0.46845238095238095,
        "mean_phase1_fixed": 0.39177777777777767,
        "mean_overlap_buggy": 0.3389847489216004,
        "mean_overlap_fixed": 0.7854734597660546,
        "mean_n_refined_buggy": 1.4210526315789473,
        "mean_n_refined_fixed": 1.5789473684210527
      }
    ]
  },
  {
    "cell": "N5_t10",
    "N": 5,
    "t": 1.0,
    "n_total": 400,
    "n_conditioned": 83,
    "n_recovery": 3,
    "n_regression": 9,
    "n_both": 43,
    "n_neither": 28,
    "table_path": "/Users/kabirmoghe/Developer/Thesis/docs/swing_analysis/per_cell/N5_t10__swing_table.csv",
    "png_path": "/Users/kabirmoghe/Developer/Thesis/docs/swing_analysis/per_cell/N5_t10__histograms.png",
    "rows": [
      {
        "category": "both",
        "n": 43,
        "mean_n_train": 3.511627906976744,
        "mean_n_test": 1.0930232558139534,
        "mean_phase1_buggy": 0.6635483870967742,
        "mean_phase1_fixed": 0.6794956140350877,
        "mean_overlap_buggy": 0.3356143276238561,
        "mean_overlap_fixed": 0.8072647201873531,
        "mean_n_refined_buggy": 1.4186046511627908,
        "mean_n_refined_fixed": 1.7674418604651163
      },
      {
        "category": "regression",
        "n": 9,
        "mean_n_train": 3.0,
        "mean_n_test": 1.0,
        "mean_phase1_buggy": 0.4690476190476191,
        "mean_phase1_fixed": 0.33333333333333337,
        "mean_overlap_buggy": 0.3283350695542465,
        "mean_overlap_fixed": 0.8324791860652155,
        "mean_n_refined_buggy": 1.3333333333333333,
        "mean_n_refined_fixed": 1.1111111111111112
      },
      {
        "category": "recovery",
        "n": 3,
        "mean_n_train": 4.0,
        "mean_n_test": 1.0,
        "mean_phase1_buggy": 0.6666666666666666,
        "mean_phase1_fixed": 0.6333333333333333,
        "mean_overlap_buggy": 0.27468944099378884,
        "mean_overlap_fixed": 0.8620461036311708,
        "mean_n_refined_buggy": 0.6666666666666666,
        "mean_n_refined_fixed": 1.3333333333333333
      },
      {
        "category": "neither",
        "n": 28,
        "mean_n_train": 3.5357142857142856,
        "mean_n_test": 1.0357142857142858,
        "mean_phase1_buggy": 0.4879678362573099,
        "mean_phase1_fixed": 0.4215277777777777,
        "mean_overlap_buggy": 0.3202714483938437,
        "mean_overlap_fixed": 0.7800069944659139,
        "mean_n_refined_buggy": 1.5357142857142858,
        "mean_n_refined_fixed": 1.2142857142857142
      }
    ]
  }
]